{
  "userId": "e3764a66-5aa5-47c4-85f6-4078d99f5a4d",
  "cart": {
    "data": {
      "cart": {
        "id": "95e62b6d-9924-490e-80e6-70e22f80cb1e",
        "name": "default",
        "itemsCount": 2,
        "itemsQuantity": 2,
        "total": {
          "amount": 62.4,
          "formattedAmount": "$62.40"
        },
        "subTotal": {
          "amount": 52,
          "formattedAmount": "$52.00"
        },
        "items": [
          {
            "id": "a9dc4b88-b2ce-413a-849e-bed4d5b8135d",
            "productId": "38dbe95c-3f46-48ff-bb9a-8bd96f475214",
            "name": "Configurable Hat",
            "sku": "Configuration-YER-80407217",
            "quantity": 1,
            "configurationItems": [
              {
                "id": "58c6d958-6426-4db5-9de9-5400862451f6",
                "productId": "42ec462f-4bb3-4e12-8068-6d5cdf59fbe1",
                "name": "Red hat",
                "quantity": 1,
                "type": "Product",
                "customText": null
              }
            ],
            "listPrice": {
              "amount": 24,
              "formattedAmount": "$24.00"
            },
            "extendedPrice": {
              "amount": 24,
              "formattedAmount": "$24.00"
            }
          },
          {
            "id": "8394396c-18af-401c-9157-34ac3757e0c4",
            "productId": "38dbe95c-3f46-48ff-bb9a-8bd96f475214",
            "name": "Configurable Hat",
            "sku": "Configuration-YER-80407217",
            "quantity": 1,
            "configurationItems": [
              {
                "id": "dc8a2ec0-3488-4692-9cb5-b3fa5b36e537",
                "productId": "59e78525-07db-43d0-bfcc-c670b7c31862",
                "name": "Green hat",
                "quantity": 1,
                "type": "Product",
                "customText": null
              }
            ],
            "listPrice": {
              "amount": 28,
              "formattedAmount": "$28.00"
            },
            "extendedPrice": {
              "amount": 28,
              "formattedAmount": "$28.00"
            }
          }
        ]
      }
    }
  }
}